{"date_of_filing": "2019-10-23", "cino": "ASGA010009162019", "dt_regis": "2019-10-23", "fil_no": 266, "fil_year": 2019, "reg_no": 44, "reg_year": 2019, "date_first_list": "2019-10-24", "date_next_list": "2020-06-01", "archive": "N", "date_of_decision": null, "disp_nature": 0, "purpose_next": 22, "court_no": 10, "pet_name": "State Of Assam", "pet_adv": "A.P.P", "res_name": "Abu Taleb", "res_adv": "", "res_legal_heir": "N", "pet_legal_heir": "N", "hide_pet_name": "N", "hide_res_name": "N", "pet_status": 0, "res_status": 0, "under_act1": 0, "under_act2": 0, "under_act3": 0, "under_act4": 0, "under_sec1": "", "under_sec2": "", "under_sec3": "", "under_sec4": "", "fir_no": "", "police_st_code": 0, "fir_year": 0, "lower_court_code": 0, "lower_court": "", "lower_court_dec_dt": 0, "case_no": "212500000442019", "goshwara_no": 0, "date_last_list": "2020-04-18", "main_matter_cino": "                ", "main_case_no": "               ", "purpose_name": "Appereance", "type_name": "Special POCSO", "petNameAdd": "1) State Of Assam<br />&nbsp;&nbsp;&nbsp;&nbsp;Advocate - A.P.P", "str_error": null, "desgname": "Addl. District & Sessions Judge, Goalpara", "resNameAdd": "1) Abu Taleb", "str_error1": null, "fir_details": {"no.": "388", "police_station": "GOALPARA", "year": "2018"}, "transfer": [{"Transfer Date": "24-10-2019", "From Court No. and Judge": "1 - District and Sessions Judge, Goalpara.", "To Court No. and Judge": "10 - Addl. District & Sessions Judge, Goalpara"}], "courtno": 10, "ldesgname": "", "desgcode": 10, "judcode": 34, "jcode": 34, "petparty_name": "State Of Assam", "resparty_name": "Abu Taleb", "court_name": "District and Sessions Judge", "est_code": "ASGA01", "state_code": "6", "district_code": "18", "state_name": "Assam", "district_name": "Goalpara", "transfer_est_flag": null, "writinfo": null, "processes": [], "complex_code": 103, "court_code": "1", "sub_matter": {}, "main_matter": {}, "link_cases": [], "subordinate_court": {}, "acts": [{"act": "Indian Penal Code", "sections": ["363"]}, {"act": "Protection of Children From Sexual Offences Act", "sections": ["4", ""]}], "orders": [], "judgment": {"no.": null, "date": null, "link": null, "path": null, "word_count": null, "language": null, "error": null}, "history": [{"Judge": "Addl. District & Sessions Judge, Goalpara", "Business On Date": "24-10-2019", "Hearing Date": "29-11-2019", "Purpose of hearing": "Appereance", "business_details": {"Business": "App", "Next Purpose": "Appereance", "Next Hearing Date": "29-11-2019"}}, {"Judge": "Addl. District & Sessions Judge, Goalpara", "Business On Date": "29-11-2019", "Hearing Date": "28-01-2020", "Purpose of hearing": "Appereance", "business_details": {"Presentee": ["State Of Assam", "A.P.P", "Abu Taleb"], "Business": "for appearence", "Next Purpose": "Appereance", "Next Hearing Date": "28-01-2020"}}, {"Judge": "Addl. District & Sessions Judge, Goalpara", "Business On Date": "28-01-2020", "Hearing Date": "12-03-2020", "Purpose of hearing": "Appereance", "business_details": {"Business": "--", "Next Purpose": "Appereance", "Next Hearing Date": "12-03-2020"}}, {"Judge": "Addl. District & Sessions Judge, Goalpara", "Business On Date": "12-03-2020", "Hearing Date": "18-04-2020", "Purpose of hearing": "Appereance", "business_details": {"Business": "Appearance", "Next Purpose": "Appereance", "Next Hearing Date": "18-04-2020"}}, {"Judge": "Addl. District & Sessions Judge, Goalpara", "Business On Date": "18-04-2020", "Hearing Date": "01-06-2020", "Purpose of hearing": "Appereance", "business_details": {"Business": "--", "Next Purpose": "Appereance", "Next Hearing Date": "01-06-2020"}}], "ia_filings": [], "files": []}
